pykx/__init__.py
pykx/_ipc.c
pykx/_ipc.cp311-win_amd64.pyd
pykx/_ipc.pxd
pykx/_ipc.pyx
pykx/_numpy.c
pykx/_numpy.cp311-win_amd64.pyd
pykx/_pyarrow.py
pykx/_pykx_helpers.c
pykx/_pykx_helpers.cp311-win_amd64.pyd
pykx/_tcore.c
pykx/_version.py
pykx/_wrappers.c
pykx/_wrappers.cp311-win_amd64.pyd
pykx/_wrappers.pxd
pykx/_wrappers.pyx
pykx/cast.py
pykx/compress_encrypt.py
pykx/config.py
pykx/console.py
pykx/constants.py
pykx/core.c
pykx/core.cp311-win_amd64.pyd
pykx/core.pxd
pykx/core.pyx
pykx/ctx.py
pykx/db.py
pykx/embedded_q.py
pykx/exceptions.py
pykx/help.py
pykx/ipc.py
pykx/license.py
pykx/nbextension.py
pykx/numpy_conversions.c
pykx/numpy_conversions.cp311-win_amd64.pyd
pykx/p.k
pykx/pykx.c
pykx/pykx.dll
pykx/pykx.exp
pykx/pykx.lib
pykx/pykx.q
pykx/pykx_init.q_
pykx/pykxq.c
pykx/pykxq.dll
pykx/pykxq.exp
pykx/pykxq.lib
pykx/python.c
pykx/query.py
pykx/random.py
pykx/read.py
pykx/register.py
pykx/reimporter.py
pykx/remote.py
pykx/schema.py
pykx/serialize.py
pykx/streamlit.py
pykx/system.py
pykx/tick.py
pykx/toq.c
pykx/toq.cp311-win_amd64.pyd
pykx/toq.pyx
pykx/util.py
pykx/wrappers.py
pykx/write.py
pykx/docs/api/pykx-execution/q.md
pykx/extensions/chained_tick.q
pykx/extensions/dashboards.q
pykx/extensions/gateway.q
pykx/extensions/hdb.q
pykx/extensions/plant.q
pykx/extensions/rdb.q
pykx/include/foreign.h
pykx/include/k.h
pykx/include/py.h
pykx/include/unlicensed_getitem.h
pykx/include/vector_conversion.h
pykx/lib/bq.q_
pykx/lib/csvutil.q
pykx/lib/dbmaint.q
pykx/lib/html.q
pykx/lib/kurl.q_
pykx/lib/kurl.sidecar.q_
pykx/lib/kxic.k
pykx/lib/licmet.q_
pykx/lib/objstor.q_
pykx/lib/pykx.q
pykx/lib/pykx_init.q_
pykx/lib/q.k
pykx/lib/qlog.q_
pykx/lib/read.q
pykx/lib/rest.q_
pykx/lib/s.k_
pykx/lib/write.q
pykx/lib/4-1-libs/bq.q_
pykx/lib/4-1-libs/csvutil.q
pykx/lib/4-1-libs/dbmaint.q
pykx/lib/4-1-libs/html.q
pykx/lib/4-1-libs/kurl.q_
pykx/lib/4-1-libs/kurl.sidecar.q_
pykx/lib/4-1-libs/kxic.k
pykx/lib/4-1-libs/licmet.q_
pykx/lib/4-1-libs/objstor.q_
pykx/lib/4-1-libs/pykx.q
pykx-3.1.5.dist-info/LICENSE.txt
pykx-3.1.5.dist-info/METADATA
pykx-3.1.5.dist-info/WHEEL
pykx-3.1.5.dist-info/top_level.txt
pykx-3.1.5.dist-info/RECORD
