Metadata-Version: 2.1
Name: pykx
Version: 3.1.5
Summary: An interface between Python and q
Home-page: https://github.com/KxSystems/pykx
Author: KX
Author-email: KX <pykx@kx.com>
License: All files contained within this repository are not covered by a single license. The following outlines the differences.
Project-URL: homepage, https://code.kx.com/pykx
Project-URL: documentation, https://code.kx.com/pykx
Project-URL: repository, https://github.com/KxSystems/pykx
Project-URL: changelog, https://code.kx.com/pykx/release-notes/changelog.html
Keywords: pykx,q,kx,database,ffi
Classifier: Development Status :: 5 - Production/Stable
Classifier: Environment :: Console
Classifier: Environment :: Other Environment
Classifier: Framework :: Flake8
Classifier: Framework :: Pytest
Classifier: Intended Audience :: Developers
Classifier: Intended Audience :: Financial and Insurance Industry
Classifier: Intended Audience :: Healthcare Industry
Classifier: Intended Audience :: Information Technology
Classifier: Intended Audience :: Manufacturing
Classifier: Intended Audience :: Other Audience
Classifier: Intended Audience :: Science/Research
Classifier: Intended Audience :: Telecommunications Industry
Classifier: License :: Other/Proprietary License
Classifier: Operating System :: MacOS
Classifier: Operating System :: Microsoft :: Windows
Classifier: Operating System :: POSIX :: Linux
Classifier: Programming Language :: C
Classifier: Programming Language :: Cython
Classifier: Programming Language :: Other
Classifier: Programming Language :: Other Scripting Engines
Classifier: Programming Language :: Python :: 3.7
Classifier: Programming Language :: Python :: 3.8
Classifier: Programming Language :: Python :: 3.9
Classifier: Programming Language :: Python :: 3.10
Classifier: Programming Language :: Python :: 3.11
Classifier: Programming Language :: Python :: 3 :: Only
Classifier: Programming Language :: Python :: Implementation :: CPython
Classifier: Topic :: Database
Classifier: Topic :: Database :: Database Engines/Servers
Classifier: Topic :: Database :: Front-Ends
Classifier: Topic :: Software Development
Classifier: Topic :: Software Development :: Interpreters
Classifier: Topic :: Software Development :: Libraries
Classifier: Typing :: Typed
Requires-Python: >=3.7
License-File: LICENSE.txt
Requires-Dist: pytz>=2022.1
Requires-Dist: toml~=0.10.2
Requires-Dist: dill>=0.2.0
Requires-Dist: requests>=2.25.0
Requires-Dist: numpy>=1.22; python_version == "3.10"
Requires-Dist: numpy<2.3.0,>=1.23; python_version == "3.11"
Requires-Dist: numpy<2.3.0,>=1.26; python_version == "3.12"
Requires-Dist: numpy<2.3.0,>=1.26; python_version == "3.13"
Requires-Dist: numpy~=1.20; python_version == "3.7"
Requires-Dist: numpy~=1.22; python_version == "3.8"
Requires-Dist: pandas<2.0,>=1.2; python_version == "3.8"
Requires-Dist: numpy~=1.22; python_version == "3.9"
Requires-Dist: pandas<=2.3.0,>=1.2; python_version > "3.8"
Provides-Extra: all
Requires-Dist: black==22.1.0; extra == "all"
Requires-Dist: griffe==0.17.0; extra == "all"
Requires-Dist: jupyter==1.0.0; extra == "all"
Requires-Dist: mkdocs~=1.5.0; extra == "all"
Requires-Dist: markdown==3.3.7; extra == "all"
Requires-Dist: markdown-grid-tables==0.0.1; extra == "all"
Requires-Dist: mkdocs-autorefs==0.4.1; extra == "all"
Requires-Dist: mkdocs-click==0.5.0; extra == "all"
Requires-Dist: mkdocs-exclude==1.0.2; extra == "all"
Requires-Dist: mkdocs-exclude-search==0.6.6; extra == "all"
Requires-Dist: mkdocs-jupyter~=0.24; extra == "all"
Requires-Dist: mkdocs-material~=9.4.5; extra == "all"
Requires-Dist: mkdocs-render-swagger-plugin==0.0.3; extra == "all"
Requires-Dist: mkdocs-spellcheck==0.2.0; extra == "all"
Requires-Dist: mkdocstrings[python]==0.18.0; extra == "all"
Requires-Dist: plotly==6.3.0; extra == "all"
Requires-Dist: pygments~=2.12; extra == "all"
Requires-Dist: pymdown-extensions>=9.3; extra == "all"
Requires-Dist: matplotlib; extra == "all"
Requires-Dist: seaborn; extra == "all"
Requires-Dist: kaleido~=0.2.0; extra == "all"
Requires-Dist: find-libpython~=0.2; extra == "all"
Requires-Dist: flake8==4.0.1; extra == "all"
Requires-Dist: flake8-bugbear==22.1.11; extra == "all"
Requires-Dist: flake8-colors==0.1.9; extra == "all"
Requires-Dist: flake8-docstrings==1.6.0; extra == "all"
Requires-Dist: flake8-import-order==0.18.1; extra == "all"
Requires-Dist: pep8-naming==0.12.1; extra == "all"
Requires-Dist: pyproject-flake8==0.0.1a2; extra == "all"
Requires-Dist: pyarrow<19.0.0,>=3.0.0; extra == "all"
Requires-Dist: psutil>=5.0.0; extra == "all"
Requires-Dist: ast2json~=0.3; extra == "all"
Requires-Dist: coverage[toml]==6.3.2; extra == "all"
Requires-Dist: Cython~=3.0.0; extra == "all"
Requires-Dist: pytest==7.1.2; extra == "all"
Requires-Dist: pytest-asyncio==0.18.3; extra == "all"
Requires-Dist: pytest-benchmark==3.4.1; extra == "all"
Requires-Dist: pytest-cov==3.0.0; extra == "all"
Requires-Dist: pytest-randomly==3.11.0; extra == "all"
Requires-Dist: pytest-xdist==2.5.0; extra == "all"
Requires-Dist: pytest-order==1.1.0; extra == "all"
Requires-Dist: pytest-rerunfailures==10.3; extra == "all"
Requires-Dist: pytest-timeout>=2.0.0; extra == "all"
Requires-Dist: IPython; extra == "all"
Requires-Dist: beautifulsoup4==4.10.0; extra == "all"
Requires-Dist: markdown2==2.5.0; extra == "all"
Requires-Dist: streamlit~=1.28; python_version > "3.7" and extra == "all"
Requires-Dist: torch>2.1; (sys_platform != "darwin" or platform_machine != "x86_64" or python_version <= "3.12") and extra == "all"
Provides-Extra: dashboards
Requires-Dist: ast2json~=0.3; extra == "dashboards"
Provides-Extra: debug
Requires-Dist: find-libpython~=0.2; extra == "debug"
Provides-Extra: doc
Requires-Dist: black==22.1.0; extra == "doc"
Requires-Dist: griffe==0.17.0; extra == "doc"
Requires-Dist: jupyter==1.0.0; extra == "doc"
Requires-Dist: mkdocs~=1.5.0; extra == "doc"
Requires-Dist: markdown==3.3.7; extra == "doc"
Requires-Dist: markdown-grid-tables==0.0.1; extra == "doc"
Requires-Dist: mkdocs-autorefs==0.4.1; extra == "doc"
Requires-Dist: mkdocs-click==0.5.0; extra == "doc"
Requires-Dist: mkdocs-exclude==1.0.2; extra == "doc"
Requires-Dist: mkdocs-exclude-search==0.6.6; extra == "doc"
Requires-Dist: mkdocs-jupyter~=0.24; extra == "doc"
Requires-Dist: mkdocs-material~=9.4.5; extra == "doc"
Requires-Dist: mkdocs-render-swagger-plugin==0.0.3; extra == "doc"
Requires-Dist: mkdocs-spellcheck==0.2.0; extra == "doc"
Requires-Dist: mkdocstrings[python]==0.18.0; extra == "doc"
Requires-Dist: plotly==6.3.0; extra == "doc"
Requires-Dist: pygments~=2.12; extra == "doc"
Requires-Dist: pymdown-extensions>=9.3; extra == "doc"
Requires-Dist: matplotlib; extra == "doc"
Requires-Dist: seaborn; extra == "doc"
Requires-Dist: kaleido~=0.2.0; extra == "doc"
Provides-Extra: help
Requires-Dist: beautifulsoup4==4.10.0; extra == "help"
Requires-Dist: markdown2==2.5.0; extra == "help"
Provides-Extra: lint
Requires-Dist: flake8==4.0.1; extra == "lint"
Requires-Dist: flake8-bugbear==22.1.11; extra == "lint"
Requires-Dist: flake8-colors==0.1.9; extra == "lint"
Requires-Dist: flake8-docstrings==1.6.0; extra == "lint"
Requires-Dist: flake8-import-order==0.18.1; extra == "lint"
Requires-Dist: pep8-naming==0.12.1; extra == "lint"
Requires-Dist: pyproject-flake8==0.0.1a2; extra == "lint"
Provides-Extra: pyarrow
Requires-Dist: pyarrow<19.0.0,>=3.0.0; extra == "pyarrow"
Provides-Extra: streaming
Requires-Dist: psutil>=5.0.0; extra == "streaming"
Provides-Extra: streamlit
Requires-Dist: streamlit~=1.28; python_version > "3.7" and extra == "streamlit"
Provides-Extra: test
Requires-Dist: coverage[toml]==6.3.2; extra == "test"
Requires-Dist: Cython~=3.0.0; extra == "test"
Requires-Dist: pytest==7.1.2; extra == "test"
Requires-Dist: pytest-asyncio==0.18.3; extra == "test"
Requires-Dist: pytest-benchmark==3.4.1; extra == "test"
Requires-Dist: pytest-cov==3.0.0; extra == "test"
Requires-Dist: pytest-randomly==3.11.0; extra == "test"
Requires-Dist: pytest-xdist==2.5.0; extra == "test"
Requires-Dist: pytest-order==1.1.0; extra == "test"
Requires-Dist: pytest-rerunfailures==10.3; extra == "test"
Requires-Dist: psutil>=5.0.0; extra == "test"
Requires-Dist: pytest-timeout>=2.0.0; extra == "test"
Requires-Dist: IPython; extra == "test"
Provides-Extra: torch
Requires-Dist: torch>2.1; (sys_platform != "darwin" or platform_machine != "x86_64" or python_version <= "3.12") and extra == "torch"
